sshdashboard/__init__.py
sshdashboard/appconfig.py
sshdashboard/appversion.py
sshdashboard/args.py
sshdashboard/config.json
sshdashboard/connector.py
sshdashboard/flaskthread.py
sshdashboard/influxdbclient.py
sshdashboard/main.py
sshdashboard/metrics.py
sshdashboard/mqttclient.py
sshdashboard/observer.py
sshdashboard/observerbase.py
sshdashboard/systeminfocache.py
sshdashboard/systeminfoentry.py
sshdashboard/css/style.css
sshdashboard/js/common.js
sshdashboard/templates/details.html
sshdashboard/templates/overview.html
ssh_dashboard-1.6.0.dist-info/LICENSE.txt
ssh_dashboard-1.6.0.dist-info/METADATA
ssh_dashboard-1.6.0.dist-info/WHEEL
ssh_dashboard-1.6.0.dist-info/entry_points.txt
ssh_dashboard-1.6.0.dist-info/top_level.txt
ssh_dashboard-1.6.0.dist-info/RECORD
